gqlmod_github/__init__.py
gqlmod_github/_app_base.py
gqlmod_github/app.py
gqlmod_github/app_async.py
gqlmod_github-0.6.1.dist-info/LICENSE
gqlmod_github-0.6.1.dist-info/METADATA
gqlmod_github-0.6.1.dist-info/WHEEL
gqlmod_github-0.6.1.dist-info/entry_points.txt
gqlmod_github-0.6.1.dist-info/top_level.txt
gqlmod_github-0.6.1.dist-info/RECORD
