Metadata-Version: 2.1
Name: gqlmod-github
Version: 0.6.1
Summary: GitHub provider for gqlmod
Home-page: https://github.com/gqlmod/gqlmod-github
Author: Jamie Bliss
Author-email: jamie@ivyleav.es
License: LGPL
Platform: UNKNOWN
Classifier: Programming Language :: Python :: 3
Classifier: Programming Language :: Python :: 3.7
Classifier: License :: OSI Approved :: GNU Lesser General Public License v3 or later (LGPLv3+)
Classifier: Operating System :: OS Independent
Requires-Python: >=3.7
Requires-Dist: gqlmod (~=0.8.0)
Provides-Extra: app
Requires-Dist: jwcrypto ; extra == 'app'
Requires-Dist: python-dateutil ; extra == 'app'
Provides-Extra: async
Requires-Dist: gqlmod[aiohttp] ; extra == 'async'
Requires-Dist: aiohttp ; extra == 'async'
Provides-Extra: sync
